{
  "id": "5209cef8-8d83-412f-a9e9-4105f894c611",
  "prevId": "6240c031-c985-4120-b381-2acf1184b6b4",
  "version": "7",
  "dialect": "postgresql",
  "tables": {
    "public.comments": {
      "name": "comments",
      "schema": "",
      "columns": {
        "id": {
          "name": "id",
          "type": "text",
          "primaryKey": true,
          "notNull": true
        },
        "post_id": {
          "name": "post_id",
          "type": "text",
          "primaryKey": false,
          "notNull": true
        },
        "parent_comment_id": {
          "name": "parent_comment_id",
          "type": "text",
          "primaryKey": false,
          "notNull": false
        },
        "parent_comment_author": {
          "name": "parent_comment_author",
          "type": "text",
          "primaryKey": false,
          "notNull": false
        },
        "parent_comment_author_id": {
          "name": "parent_comment_author_id",
          "type": "text",
          "primaryKey": false,
          "notNull": false
        },
        "content": {
          "name": "content",
          "type": "text",
          "primaryKey": false,
          "notNull": true
        },
        "author": {
          "name": "author",
          "type": "text",
          "primaryKey": false,
          "notNull": true
        },
        "author_id": {
          "name": "author_id",
          "type": "text",
          "primaryKey": false,
          "notNull": true
        },
        "user_image_url": {
          "name": "user_image_url",
          "type": "text",
          "primaryKey": false,
          "notNull": false
        },
        "likes": {
          "name": "likes",
          "type": "jsonb",
          "primaryKey": false,
          "notNull": true
        },
        "created_at": {
          "name": "created_at",
          "type": "timestamp with time zone",
          "primaryKey": false,
          "notNull": true,
          "default": "now()"
        }
      },
      "indexes": {},
      "foreignKeys": {
        "comments_parent_comment_id_comments_id_fk": {
          "name": "comments_parent_comment_id_comments_id_fk",
          "tableFrom": "comments",
          "tableTo": "comments",
          "columnsFrom": [
            "parent_comment_id"
          ],
          "columnsTo": [
            "id"
          ],
          "onDelete": "cascade",
          "onUpdate": "no action"
        }
      },
      "compositePrimaryKeys": {},
      "uniqueConstraints": {}
    },
    "public.posts": {
      "name": "posts",
      "schema": "",
      "columns": {
        "id": {
          "name": "id",
          "type": "text",
          "primaryKey": true,
          "notNull": true
        },
        "content": {
          "name": "content",
          "type": "text",
          "primaryKey": false,
          "notNull": true
        },
        "author": {
          "name": "author",
          "type": "text",
          "primaryKey": false,
          "notNull": true
        },
        "author_id": {
          "name": "author_id",
          "type": "text",
          "primaryKey": false,
          "notNull": true
        },
        "user_image_url": {
          "name": "user_image_url",
          "type": "text",
          "primaryKey": false,
          "notNull": true
        },
        "likes": {
          "name": "likes",
          "type": "jsonb",
          "primaryKey": false,
          "notNull": true
        },
        "created_at": {
          "name": "created_at",
          "type": "timestamp with time zone",
          "primaryKey": false,
          "notNull": true,
          "default": "now()"
        },
        "slug": {
          "name": "slug",
          "type": "text",
          "primaryKey": false,
          "notNull": true
        }
      },
      "indexes": {},
      "foreignKeys": {},
      "compositePrimaryKeys": {},
      "uniqueConstraints": {}
    },
    "public.users": {
      "name": "users",
      "schema": "",
      "columns": {
        "id": {
          "name": "id",
          "type": "text",
          "primaryKey": true,
          "notNull": true
        },
        "user_name": {
          "name": "user_name",
          "type": "text",
          "primaryKey": false,
          "notNull": true
        },
        "user_id": {
          "name": "user_id",
          "type": "text",
          "primaryKey": false,
          "notNull": true
        },
        "created_at": {
          "name": "created_at",
          "type": "timestamp with time zone",
          "primaryKey": false,
          "notNull": true,
          "default": "now()"
        }
      },
      "indexes": {},
      "foreignKeys": {},
      "compositePrimaryKeys": {},
      "uniqueConstraints": {}
    }
  },
  "enums": {},
  "schemas": {},
  "sequences": {},
  "_meta": {
    "columns": {},
    "schemas": {},
    "tables": {}
  }
}